colmena/__init__.py
colmena/context.py
colmena/exceptions.py
colmena/logger.py
colmena/role.py
colmena/service.py
colmena/abstractions/__init__.py
colmena/abstractions/channel_abstraction.py
colmena/abstractions/data_abstraction.py
colmena/abstractions/metric_abstraction.py
colmena/building_tool/__init__.py
colmena/building_tool/colmena_build.py
colmena/decorators/__init__.py
colmena/decorators/base_abstraction.py
colmena/decorators/base_image.py
colmena/decorators/behavior_types.py
colmena/decorators/channel.py
colmena/decorators/data.py
colmena/decorators/dependencies.py
colmena/decorators/kpi.py
colmena/decorators/metric.py
colmena/decorators/requirements.py
colmena/decorators/version.py
colmena/implementations/__init__.py
colmena/implementations/communications.py
colmena/implementations/context_awareness.py
colmena/implementations/pyre_client.py
colmena/implementations/zenoh_client.py
colmena/implementations/zenoh_config.json5
colmena/implementations/pyre/__init__.py
colmena/implementations/pyre/message_converter.py
colmena/implementations/pyre/receiver_selector.py
colmena/templates/Dockerfile
colmena/templates/pyproject.toml
colmena_swarm_pm_fcas-0.1.9.dist-info/METADATA
colmena_swarm_pm_fcas-0.1.9.dist-info/WHEEL
colmena_swarm_pm_fcas-0.1.9.dist-info/entry_points.txt
colmena_swarm_pm_fcas-0.1.9.dist-info/licenses/LICENSE
colmena_swarm_pm_fcas-0.1.9.dist-info/RECORD
